{
    "uuid": "divvy.user_stale_access_keys",
    "name": "Cloud User API Key Audit",
    "category": "Best Practices",
    "description": "Identify cloud users with API key credentials which should be rotated",
    "instructions": {
        "actions": [
            {
                "config": {},
                "name": "divvy.action.mark_non_compliant",
                "run_when_result_is": true
            }
        ],
        "filters": [
            {
                "config": {
                    "days": 90
                },
                "name": "divvy.filter.service_user_access_key_age_at_least"
            }
        ],
        "groups": [],
        "hookpoints": [
            "divvycloud.resource.created",
            "divvycloud.resource.modified"
        ],
        "ondemand_enabled": true,
        "resource_types": [
            "serviceuser"
        ]
    }
}
